{
  "symbol": "1801.T",
  "name": "TAISEI CORP",
  "sector": "Industrials",
  "industry": "Engineering & Construction",
  "currency": "JPY",
  "price": 13310.0,
  "market_cap": 2169651331072.0,
  "per": 12.973469,
  "forward_per": 27.962185,
  "pbr": 2.2884855,
  "psr": 1.0385624,
  "roe": null,
  "roa": null,
  "profit_margin": 0.081379995,
  "operating_margin": 0.09766,
  "dividend_yield": 0.028900000000000002,
  "dividend_yield_trailing": 0.023538345,
  "payout_ratio": 0.3023,
  "revenue_growth": null,
  "earnings_growth": null,
  "debt_to_equity": 47.08,
  "current_ratio": 1.187,
  "free_cashflow": null,
  "beta": 0.566,
  "fifty_two_week_high": 20680.0,
  "fifty_two_week_low": 7831.0,
  "_market_data_updated": "2026-06-09T10:56:09.112266+00:00"
}