{
  "symbol": "1801.T",
  "name": "TAISEI CORP",
  "sector": "Industrials",
  "industry": "Engineering & Construction",
  "currency": "JPY",
  "price": 13520.0,
  "market_cap": 2203883405312.0,
  "per": 13.184585,
  "forward_per": 28.403362,
  "pbr": 2.3245897,
  "psr": 1.0549486,
  "roe": 0.18494,
  "roa": 0.045679998,
  "profit_margin": 0.081379995,
  "operating_margin": 0.09922,
  "dividend_yield": 0.0279,
  "dividend_yield_trailing": 0.022794118,
  "payout_ratio": 0.3023,
  "revenue_growth": 0.055,
  "earnings_growth": 0.814,
  "debt_to_equity": 47.08,
  "current_ratio": 1.187,
  "free_cashflow": 39856250880.0,
  "beta": 0.556,
  "fifty_two_week_high": 20680.0,
  "fifty_two_week_low": 8381.0,
  "_market_data_updated": "2026-07-14T09:52:02.703154+00:00"
}