{
  "symbol": "1860.T",
  "name": "TODA CORP",
  "sector": "Industrials",
  "industry": "Engineering & Construction",
  "currency": "JPY",
  "price": 1605.5,
  "market_cap": 475292270592.0,
  "per": 13.010534,
  "forward_per": 17.604168,
  "pbr": 1.2279694,
  "psr": 0.7360462,
  "roe": 0.09923001,
  "roa": 0.02485,
  "profit_margin": 0.05727,
  "operating_margin": 0.05298,
  "dividend_yield": 0.0379,
  "dividend_yield_trailing": 0.0,
  "payout_ratio": 0.4702,
  "revenue_growth": -0.099,
  "earnings_growth": -0.219,
  "debt_to_equity": 56.948,
  "current_ratio": 1.363,
  "free_cashflow": 20769748992.0,
  "beta": 0.242,
  "fifty_two_week_high": 1665.0,
  "fifty_two_week_low": 885.4,
  "_market_data_updated": "2026-06-17T12:12:30.607672+00:00"
}