{
  "symbol": "2875.T",
  "name": "TOYO SUISAN KAISHA",
  "sector": "Consumer Defensive",
  "industry": "Packaged Foods",
  "currency": "JPY",
  "price": 10845.0,
  "market_cap": 1055678005248.0,
  "per": 17.221666,
  "forward_per": 17.14489,
  "pbr": 2.0926073,
  "psr": 2.0244892,
  "roe": 0.13028,
  "roa": 0.08071999,
  "profit_margin": 0.12546,
  "operating_margin": 0.16917999,
  "dividend_yield": 0.0218,
  "dividend_yield_trailing": 0.018198362,
  "payout_ratio": 0.3174,
  "revenue_growth": -0.02,
  "earnings_growth": 0.006,
  "debt_to_equity": 0.629,
  "current_ratio": 4.532,
  "free_cashflow": null,
  "beta": 0.252,
  "fifty_two_week_high": 12405.0,
  "fifty_two_week_low": 8711.0,
  "_market_data_updated": "2026-04-16T09:14:14.203178+00:00"
}