{
  "symbol": "2914.T",
  "name": "JAPAN TOBACCO INC",
  "sector": "Consumer Defensive",
  "industry": "Tobacco",
  "currency": "JPY",
  "price": 5714.0,
  "market_cap": 10144569098240.0,
  "per": 20.322948,
  "forward_per": 18.976454,
  "pbr": 2.482196,
  "psr": 2.9254673,
  "roe": 0.12149999,
  "roa": 0.0639,
  "profit_margin": 0.14712,
  "operating_margin": 0.24619,
  "dividend_yield": 0.0426,
  "dividend_yield_trailing": 0.041197184,
  "payout_ratio": 0.8325,
  "revenue_growth": null,
  "earnings_growth": null,
  "debt_to_equity": 45.787,
  "current_ratio": 1.926,
  "free_cashflow": 181630992384.0,
  "beta": 0.162,
  "fifty_two_week_high": 6182.0,
  "fifty_two_week_low": 3761.0,
  "_market_data_updated": "2026-03-06T08:32:01.778913+00:00"
}