{
  "symbol": "3086.T",
  "name": "J FRONT RETAILING CO LTD",
  "sector": "Consumer Cyclical",
  "industry": "Department Stores",
  "currency": "JPY",
  "price": 2487.0,
  "market_cap": 618399727616.0,
  "per": 22.03615,
  "forward_per": 19.551888,
  "pbr": 1.4880186,
  "psr": 1.3893688,
  "roe": 0.06597,
  "roa": 0.02657,
  "profit_margin": 0.063540004,
  "operating_margin": 0.07117,
  "dividend_yield": 0.022400000000000003,
  "dividend_yield_trailing": 0.0216,
  "payout_ratio": 0.47869998,
  "revenue_growth": -0.071,
  "earnings_growth": -0.154,
  "debt_to_equity": 78.658,
  "current_ratio": 0.701,
  "free_cashflow": 39428251648.0,
  "beta": 0.036,
  "fifty_two_week_high": 2796.0,
  "fifty_two_week_low": 1657.0,
  "_market_data_updated": "2026-04-20T09:54:58.943782+00:00"
}