{
  "symbol": "3088.T",
  "name": "MATSUKIYOCOCOKARA & CO",
  "sector": "Healthcare",
  "industry": "Pharmaceutical Retailers",
  "currency": "JPY",
  "price": 2424.0,
  "market_cap": 964575690752.0,
  "per": 17.337816,
  "forward_per": 17.455175,
  "pbr": 1.821573,
  "psr": 0.8773288,
  "roe": 0.10854,
  "roa": 0.0728,
  "profit_margin": 0.05098,
  "operating_margin": 0.08201,
  "dividend_yield": 0.019799999999999998,
  "dividend_yield_trailing": 0.019397441,
  "payout_ratio": 0.3361,
  "revenue_growth": null,
  "earnings_growth": null,
  "debt_to_equity": 0.285,
  "current_ratio": 2.178,
  "free_cashflow": null,
  "beta": -0.211,
  "fifty_two_week_high": 3393.0,
  "fifty_two_week_low": 2258.0,
  "_market_data_updated": "2026-03-25T08:43:27.157022+00:00"
}