{
  "symbol": "3088.T",
  "name": "MATSUKIYOCOCOKARA & CO",
  "sector": "Healthcare",
  "industry": "Pharmaceutical Retailers",
  "currency": "JPY",
  "price": 2559.0,
  "market_cap": 1018295877632.0,
  "per": 18.294252,
  "forward_per": 18.427307,
  "pbr": 1.923022,
  "psr": 0.92618996,
  "roe": 0.10854,
  "roa": 0.0728,
  "profit_margin": 0.05098,
  "operating_margin": 0.08201,
  "dividend_yield": 0.0183,
  "dividend_yield_trailing": 0.017942356,
  "payout_ratio": 0.3361,
  "revenue_growth": null,
  "earnings_growth": null,
  "debt_to_equity": 0.285,
  "current_ratio": 2.178,
  "free_cashflow": null,
  "beta": -0.208,
  "fifty_two_week_high": 3393.0,
  "fifty_two_week_low": 2258.0,
  "_market_data_updated": "2026-02-26T08:40:26.257944+00:00"
}