{
  "symbol": "3088.T",
  "name": "MATSUKIYOCOCOKARA & CO",
  "sector": "Healthcare",
  "industry": "Pharmaceutical Retailers",
  "currency": "JPY",
  "price": 2209.0,
  "market_cap": 879017459712.0,
  "per": 15.796625,
  "forward_per": 15.906964,
  "pbr": 1.6172594,
  "psr": 0.786635,
  "roe": 0.10526,
  "roa": 0.0723,
  "profit_margin": 0.04991,
  "operating_margin": 0.07439,
  "dividend_yield": 0.0248,
  "dividend_yield_trailing": 0.022168033,
  "payout_ratio": 0.3361,
  "revenue_growth": 0.069,
  "earnings_growth": -0.006,
  "debt_to_equity": 0.612,
  "current_ratio": 2.208,
  "free_cashflow": 45826498560.0,
  "beta": -0.184,
  "fifty_two_week_high": 3393.0,
  "fifty_two_week_low": 2187.0,
  "_market_data_updated": "2026-05-25T11:49:28.293389+00:00"
}