{
  "symbol": "4005.T",
  "name": "SUMITOMO CHEMICAL COMPANY",
  "sector": "Basic Materials",
  "industry": "Chemicals",
  "currency": "JPY",
  "price": 520.1,
  "market_cap": 851607879680.0,
  "per": 10.038602,
  "forward_per": 13.353016,
  "pbr": 0.826868,
  "psr": 0.3536908,
  "roe": 0.12083,
  "roa": 0.04883,
  "profit_margin": 0.04044,
  "operating_margin": 0.15158,
  "dividend_yield": 0.0258,
  "dividend_yield_trailing": 0.02295333,
  "payout_ratio": 0.2316,
  "revenue_growth": -0.079,
  "earnings_growth": 0.357,
  "debt_to_equity": 96.472,
  "current_ratio": 1.57,
  "free_cashflow": 174770749440.0,
  "beta": 0.446,
  "fifty_two_week_high": 620.6,
  "fifty_two_week_low": 306.4,
  "_market_data_updated": "2026-04-14T09:12:50.458348+00:00"
}