{
  "symbol": "4021.T",
  "name": "NISSAN CHEMICAL CORPORATION",
  "sector": "Basic Materials",
  "industry": "Chemicals",
  "currency": "JPY",
  "price": 6179.0,
  "market_cap": 828657238016.0,
  "per": 18.551655,
  "forward_per": 19.162067,
  "pbr": 3.4368963,
  "psr": 3.0468924,
  "roe": 0.19723,
  "roa": 0.11334,
  "profit_margin": 0.17052999,
  "operating_margin": 0.23549,
  "dividend_yield": 0.0362,
  "dividend_yield_trailing": 0.028627839,
  "payout_ratio": 0.5226,
  "revenue_growth": 0.153,
  "earnings_growth": 0.112,
  "debt_to_equity": 16.676,
  "current_ratio": 2.718,
  "free_cashflow": 34629623808.0,
  "beta": 0.284,
  "fifty_two_week_high": 7180.0,
  "fifty_two_week_low": 3846.0,
  "_market_data_updated": "2026-04-03T08:46:37.371770+00:00"
}