{
  "symbol": "4186.T",
  "name": "TOKYO OHKA KOGYO CO",
  "sector": "Technology",
  "industry": "Electronic Components",
  "currency": "JPY",
  "price": 10760.0,
  "market_cap": 1290129506304.0,
  "per": 38.67304,
  "forward_per": 55.125774,
  "pbr": 3.1451542,
  "psr": 11.140631,
  "roe": 0.05544,
  "roa": 0.03951,
  "profit_margin": 0.061279997,
  "operating_margin": 0.08284,
  "dividend_yield": 0.69,
  "dividend_yield_trailing": 0.0027717627,
  "payout_ratio": 0.2588,
  "revenue_growth": 0.929,
  "earnings_growth": 0.082,
  "debt_to_equity": null,
  "current_ratio": 4.035,
  "free_cashflow": null,
  "beta": 0.843,
  "fifty_two_week_high": 12925.0,
  "fifty_two_week_low": 3405.0,
  "_market_data_updated": "2026-05-15T10:17:16.634420+00:00"
}