{
  "symbol": "4502.T",
  "name": "TAKEDA PHARMACEUTICAL CO LTD",
  "sector": "Healthcare",
  "industry": "Drug Manufacturers - Specialty & Generic",
  "currency": "JPY",
  "price": 5109.0,
  "market_cap": 8071385972736.0,
  "per": 42.695972,
  "forward_per": 36.39148,
  "pbr": 1.0383085,
  "psr": 1.7913643,
  "roe": 0.02611,
  "roa": 0.02632,
  "profit_margin": 0.04256,
  "operating_margin": 0.03088,
  "dividend_yield": 0.0394,
  "dividend_yield_trailing": 0.038610037,
  "payout_ratio": 1.6717,
  "revenue_growth": 0.039,
  "earnings_growth": null,
  "debt_to_equity": 70.138,
  "current_ratio": 1.272,
  "free_cashflow": 356631117824.0,
  "beta": 0.098,
  "fifty_two_week_high": 6033.0,
  "fifty_two_week_low": 4102.0,
  "_market_data_updated": "2026-05-22T10:45:43.136465+00:00"
}