{
  "symbol": "4507.T",
  "name": "SHIONOGI & CO",
  "sector": "Healthcare",
  "industry": "Drug Manufacturers - Specialty & Generic",
  "currency": "JPY",
  "price": 3580.0,
  "market_cap": 3046494961664.0,
  "per": 17.847351,
  "forward_per": 18.72385,
  "pbr": 2.012,
  "psr": 6.546196,
  "roe": 0.13512,
  "roa": 0.06842,
  "profit_margin": 0.41863,
  "operating_margin": 0.50216,
  "dividend_yield": 0.018600000000000002,
  "dividend_yield_trailing": 0.002619315,
  "payout_ratio": 0.32880002,
  "revenue_growth": 0.235,
  "earnings_growth": 0.474,
  "debt_to_equity": 1.505,
  "current_ratio": 5.843,
  "free_cashflow": null,
  "beta": 0.08,
  "fifty_two_week_high": 3705.0,
  "fifty_two_week_low": 2153.5,
  "_market_data_updated": "2026-04-06T09:03:56.082743+00:00"
}