{
  "symbol": "4516.T",
  "name": "NIPPON SHINYAKU CO",
  "sector": "Healthcare",
  "industry": "Drug Manufacturers - Specialty & Generic",
  "currency": "JPY",
  "price": 5127.0,
  "market_cap": 345564676096.0,
  "per": 10.81007,
  "forward_per": 12.486909,
  "pbr": 1.2173,
  "psr": 2.0811255,
  "roe": 0.11224,
  "roa": 0.074499995,
  "profit_margin": 0.17977,
  "operating_margin": 0.26857,
  "dividend_yield": 0.0241,
  "dividend_yield_trailing": 0.024105754,
  "payout_ratio": 0.2616,
  "revenue_growth": 0.131,
  "earnings_growth": -0.172,
  "debt_to_equity": 0.896,
  "current_ratio": 5.641,
  "free_cashflow": 5011999744.0,
  "beta": null,
  "fifty_two_week_high": 6529.0,
  "fifty_two_week_low": 2967.0,
  "_market_data_updated": "2026-03-02T08:39:09.139584+00:00"
}