{
  "symbol": "4519.T",
  "name": "CHUGAI PHARMACEUTICAL CO",
  "sector": "Healthcare",
  "industry": "Drug Manufacturers - General",
  "currency": "JPY",
  "price": 7936.0,
  "market_cap": 13060775346176.0,
  "per": 30.13366,
  "forward_per": 33.639946,
  "pbr": 6.846296,
  "psr": 10.114996,
  "roe": 0.23707001,
  "roa": 0.17375,
  "profit_margin": 0.35021,
  "operating_margin": 0.49345002,
  "dividend_yield": 0.0167,
  "dividend_yield_trailing": 0.015472416,
  "payout_ratio": 0.4626,
  "revenue_growth": 0.115,
  "earnings_growth": 0.187,
  "debt_to_equity": null,
  "current_ratio": 4.698,
  "free_cashflow": 308219609088.0,
  "beta": 0.56,
  "fifty_two_week_high": 10700.0,
  "fifty_two_week_low": 5942.0,
  "_market_data_updated": "2026-05-19T10:58:25.236325+00:00"
}