{
  "symbol": "4631.T",
  "name": "DIC CORPORATION",
  "sector": "Basic Materials",
  "industry": "Specialty Chemicals",
  "currency": "JPY",
  "price": 3813.0,
  "market_cap": 361015017472.0,
  "per": 11.162178,
  "forward_per": 11.631029,
  "pbr": 0.76668155,
  "psr": 0.3431069,
  "roe": 0.07288,
  "roa": 0.02609,
  "profit_margin": 0.03075,
  "operating_margin": 0.044,
  "dividend_yield": 0.038,
  "dividend_yield_trailing": 0.054215234,
  "payout_ratio": 0.35119998,
  "revenue_growth": 0.011,
  "earnings_growth": -0.006,
  "debt_to_equity": 93.364,
  "current_ratio": 1.623,
  "free_cashflow": 27192750080.0,
  "beta": 0.587,
  "fifty_two_week_high": 4632.0,
  "fifty_two_week_low": 2447.0,
  "_market_data_updated": "2026-04-08T08:56:18.689006+00:00"
}