{
  "symbol": "4631.T",
  "name": "DIC CORPORATION",
  "sector": "Basic Materials",
  "industry": "Specialty Chemicals",
  "currency": "JPY",
  "price": 3668.0,
  "market_cap": 347286405120.0,
  "per": 10.738962,
  "forward_per": 11.188726,
  "pbr": 0.7375263,
  "psr": 0.3300593,
  "roe": 0.07288,
  "roa": 0.02609,
  "profit_margin": 0.03075,
  "operating_margin": 0.044,
  "dividend_yield": 0.0383,
  "dividend_yield_trailing": 0.054749522,
  "payout_ratio": 0.35119998,
  "revenue_growth": 0.011,
  "earnings_growth": -0.006,
  "debt_to_equity": 93.364,
  "current_ratio": 1.623,
  "free_cashflow": 27192750080.0,
  "beta": 0.561,
  "fifty_two_week_high": 4632.0,
  "fifty_two_week_low": 2671.0,
  "_market_data_updated": "2026-05-11T10:57:14.542279+00:00"
}