{
  "symbol": "4661.T",
  "name": "ORIENTAL LAND CO",
  "sector": "Consumer Cyclical",
  "industry": "Leisure",
  "currency": "JPY",
  "price": 2490.0,
  "market_cap": 4082894372864.0,
  "per": 33.440773,
  "forward_per": 28.473413,
  "pbr": 3.7116592,
  "psr": 5.795129,
  "roe": null,
  "roa": null,
  "profit_margin": 0.17299,
  "operating_margin": 0.15488,
  "dividend_yield": 0.64,
  "dividend_yield_trailing": 0.006003602,
  "payout_ratio": 0.2018,
  "revenue_growth": null,
  "earnings_growth": null,
  "debt_to_equity": 29.7,
  "current_ratio": 3.272,
  "free_cashflow": null,
  "beta": 0.3,
  "fifty_two_week_high": 3715.0,
  "fifty_two_week_low": 2103.0,
  "_market_data_updated": "2026-06-30T10:53:10.353693+00:00"
}