{
  "symbol": "4684.T",
  "name": "OBIC CO LTD",
  "sector": "Technology",
  "industry": "Software - Application",
  "currency": "JPY",
  "price": 4032.0,
  "market_cap": 1744447995904.0,
  "per": 23.48829,
  "forward_per": 25.19685,
  "pbr": 3.3859763,
  "psr": 12.901863,
  "roe": 0.15832,
  "roa": 0.099209994,
  "profit_margin": 0.55611,
  "operating_margin": 0.67586,
  "dividend_yield": 0.0235,
  "dividend_yield_trailing": 0.021042084,
  "payout_ratio": 0.48950002,
  "revenue_growth": 0.114,
  "earnings_growth": 0.206,
  "debt_to_equity": null,
  "current_ratio": 6.538,
  "free_cashflow": 59023998976.0,
  "beta": 0.432,
  "fifty_two_week_high": 5658.0,
  "fifty_two_week_low": 3700.0,
  "_market_data_updated": "2026-05-15T10:17:29.462365+00:00"
}