{
  "symbol": "5020.T",
  "name": "ENEOS HOLDINGS INC",
  "sector": "Energy",
  "industry": "Oil & Gas Refining & Marketing",
  "currency": "JPY",
  "price": 1222.5,
  "market_cap": 3288393842688.0,
  "per": 12.741012,
  "forward_per": 12.290137,
  "pbr": 0.97585,
  "psr": 0.2794953,
  "roe": 0.085,
  "roa": 0.02695,
  "profit_margin": 0.02199,
  "operating_margin": 0.05277,
  "dividend_yield": 0.0281,
  "dividend_yield_trailing": 0.02813405,
  "payout_ratio": 0.35419998,
  "revenue_growth": null,
  "earnings_growth": null,
  "debt_to_equity": 69.601,
  "current_ratio": 1.583,
  "free_cashflow": 243102367744.0,
  "beta": 0.265,
  "fifty_two_week_high": 1552.5,
  "fifty_two_week_low": 694.5,
  "_market_data_updated": "2026-06-11T12:06:49.805414+00:00"
}