{
  "symbol": "5108.T",
  "name": "BRIDGESTONE CORP",
  "sector": "Consumer Cyclical",
  "industry": "Auto Parts",
  "currency": "JPY",
  "price": 3462.0,
  "market_cap": 4327481278464.0,
  "per": 29.04606,
  "forward_per": 6.194532,
  "pbr": 1.1878803,
  "psr": 0.9649368,
  "roe": 0.09287,
  "roa": 0.05862,
  "profit_margin": 0.07659,
  "operating_margin": 0.11302,
  "dividend_yield": 0.038,
  "dividend_yield_trailing": 0.03357664,
  "payout_ratio": 0.96580005,
  "revenue_growth": 0.052,
  "earnings_growth": 0.302,
  "debt_to_equity": 21.403,
  "current_ratio": 2.712,
  "free_cashflow": null,
  "beta": 0.446,
  "fifty_two_week_high": 3859.0,
  "fifty_two_week_low": 2915.5,
  "_market_data_updated": "2026-06-26T10:47:32.524912+00:00"
}