{
  "symbol": "5401.T",
  "name": "NIPPON STEEL CORPORATION",
  "sector": "Basic Materials",
  "industry": "Steel",
  "currency": "JPY",
  "price": 673.9,
  "market_cap": 3522037022720.0,
  "per": null,
  "forward_per": 1.2077495,
  "pbr": 0.66180223,
  "psr": 0.37471065,
  "roe": -0.00414,
  "roa": 0.02118,
  "profit_margin": -0.00605,
  "operating_margin": 0.04259,
  "dividend_yield": 0.0356,
  "dividend_yield_trailing": 0.04072135,
  "payout_ratio": 0.4774,
  "revenue_growth": 0.206,
  "earnings_growth": -0.424,
  "debt_to_equity": 89.929,
  "current_ratio": 1.122,
  "free_cashflow": null,
  "beta": 0.715,
  "fifty_two_week_high": 704.4,
  "fifty_two_week_low": 530.0,
  "_market_data_updated": "2026-02-21T05:55:02.015997+00:00"
}