{
  "symbol": "5406.T",
  "name": "KOBE STEEL",
  "sector": "Basic Materials",
  "industry": "Steel",
  "currency": "JPY",
  "price": 1962.5,
  "market_cap": 776076591104.0,
  "per": 8.254816,
  "forward_per": 7.1102495,
  "pbr": 0.6152886,
  "psr": 0.31851047,
  "roe": 0.07621,
  "roa": 0.025880001,
  "profit_margin": 0.03846,
  "operating_margin": 0.04971,
  "dividend_yield": 0.0404,
  "dividend_yield_trailing": 0.040414248,
  "payout_ratio": 0.3364,
  "revenue_growth": -0.019,
  "earnings_growth": -0.46,
  "debt_to_equity": 57.869,
  "current_ratio": 1.63,
  "free_cashflow": 72295751680.0,
  "beta": 0.554,
  "fifty_two_week_high": 2379.5,
  "fifty_two_week_low": 1503.5,
  "_market_data_updated": "2026-05-15T10:17:41.554940+00:00"
}