{
  "symbol": "5444.T",
  "name": "YAMATO KOGYO CO",
  "sector": "Basic Materials",
  "industry": "Steel",
  "currency": "JPY",
  "price": 12625.0,
  "market_cap": 754374148096.0,
  "per": 12.316233,
  "forward_per": 14.329818,
  "pbr": 1.3924922,
  "psr": 4.703403,
  "roe": 0.10795,
  "roa": 0.00435,
  "profit_margin": 0.38898998,
  "operating_margin": 0.0254,
  "dividend_yield": 0.0322,
  "dividend_yield_trailing": 0.032232072,
  "payout_ratio": 0.39040002,
  "revenue_growth": 0.008,
  "earnings_growth": 1.392,
  "debt_to_equity": 0.128,
  "current_ratio": 13.83,
  "free_cashflow": -5237000192.0,
  "beta": 0.45,
  "fifty_two_week_high": 13205.0,
  "fifty_two_week_low": 8351.0,
  "_market_data_updated": "2026-07-13T10:55:18.790983+00:00"
}