{
  "symbol": "5802.T",
  "name": "SUMITOMO ELECTRIC INDUSTRIES",
  "sector": "Consumer Cyclical",
  "industry": "Auto Parts",
  "currency": "JPY",
  "price": 2512.0,
  "market_cap": 7836634972160.0,
  "per": 21.2198,
  "forward_per": 11.364973,
  "pbr": 2.856506,
  "psr": 1.5335367,
  "roe": 0.14953,
  "roa": 0.05641,
  "profit_margin": 0.07231,
  "operating_margin": 0.103369996,
  "dividend_yield": 0.0159,
  "dividend_yield_trailing": 0.015707875,
  "payout_ratio": 0.325,
  "revenue_growth": 0.149,
  "earnings_growth": 1.401,
  "debt_to_equity": 24.31,
  "current_ratio": 1.799,
  "free_cashflow": 162251997184.0,
  "beta": 0.89,
  "fifty_two_week_high": 3712.5,
  "fifty_two_week_low": 856.5,
  "_market_data_updated": "2026-07-23T10:15:44.484558+00:00"
}