{
  "symbol": "5803.T",
  "name": "FUJIKURA",
  "sector": "Industrials",
  "industry": "Conglomerates",
  "currency": "JPY",
  "price": 4446.0,
  "market_cap": 7360714113024.0,
  "per": 56.91244,
  "forward_per": 14.68102,
  "pbr": 14.517836,
  "psr": 6.552648,
  "roe": 0.31145,
  "roa": 0.13441,
  "profit_margin": 0.0,
  "operating_margin": 0.1758,
  "dividend_yield": 0.98,
  "dividend_yield_trailing": 0.0065811737,
  "payout_ratio": 0.344,
  "revenue_growth": null,
  "earnings_growth": null,
  "debt_to_equity": 23.258,
  "current_ratio": 2.289,
  "free_cashflow": null,
  "beta": null,
  "fifty_two_week_high": 4968.3335,
  "fifty_two_week_low": 598.6667,
  "_market_data_updated": "2026-04-01T08:58:51.084938+00:00"
}