{
  "symbol": "5803.T",
  "name": "FUJIKURA",
  "sector": "Industrials",
  "industry": "Conglomerates",
  "currency": "JPY",
  "price": 22615.0,
  "market_cap": 6240160710656.0,
  "per": 48.181606,
  "forward_per": 74.6764,
  "pbr": 12.307744,
  "psr": 5.55511,
  "roe": 0.31145,
  "roa": 0.13441,
  "profit_margin": 0.0,
  "operating_margin": 0.1758,
  "dividend_yield": 0.96,
  "dividend_yield_trailing": 0.0064342627,
  "payout_ratio": 0.344,
  "revenue_growth": null,
  "earnings_growth": null,
  "debt_to_equity": 23.258,
  "current_ratio": 2.289,
  "free_cashflow": null,
  "beta": null,
  "fifty_two_week_high": 29810.0,
  "fifty_two_week_low": 3592.0,
  "_market_data_updated": "2026-03-09T08:39:20.135138+00:00"
}