{
  "symbol": "5832.T",
  "name": "CHUGIN FINANCIAL GROUP INC",
  "sector": "Financial Services",
  "industry": "Banks - Regional",
  "currency": "JPY",
  "price": 2845.5,
  "market_cap": 505837715456.0,
  "per": 16.848244,
  "forward_per": 19.135845,
  "pbr": 0.8283797,
  "psr": 3.4784606,
  "roe": 0.06578,
  "roa": 0.00343,
  "profit_margin": 0.26563,
  "operating_margin": 0.41908002,
  "dividend_yield": 0.0287,
  "dividend_yield_trailing": 0.024769388,
  "payout_ratio": 0.4293,
  "revenue_growth": null,
  "earnings_growth": null,
  "debt_to_equity": null,
  "current_ratio": null,
  "free_cashflow": null,
  "beta": 0.149,
  "fifty_two_week_high": 3485.0,
  "fifty_two_week_low": 1470.0,
  "_market_data_updated": "2026-05-01T09:29:56.290930+00:00"
}