{
  "symbol": "6146.T",
  "name": "DISCO CORPORATION",
  "sector": "Technology",
  "industry": "Semiconductor Equipment & Materials",
  "currency": "JPY",
  "price": 67450.0,
  "market_cap": 7313639342080.0,
  "per": 58.00105,
  "forward_per": 49.561337,
  "pbr": 13.487701,
  "psr": 17.227007,
  "roe": null,
  "roa": null,
  "profit_margin": 0.0,
  "operating_margin": 0.43093,
  "dividend_yield": 0.7,
  "dividend_yield_trailing": 0.0066496977,
  "payout_ratio": 0.35979998,
  "revenue_growth": 0.168,
  "earnings_growth": 0.154,
  "debt_to_equity": null,
  "current_ratio": 3.318,
  "free_cashflow": null,
  "beta": null,
  "fifty_two_week_high": 81000.0,
  "fifty_two_week_low": 23800.0,
  "_market_data_updated": "2026-04-08T08:56:42.066542+00:00"
}