{
  "symbol": "6178.T",
  "name": "JAPAN POST HLDGS CO LTD",
  "sector": "Financial Services",
  "industry": "Banks - Regional",
  "currency": "JPY",
  "price": 2018.5,
  "market_cap": 5687067803648.0,
  "per": 16.377281,
  "forward_per": 16.215456,
  "pbr": 0.59706444,
  "psr": 0.49223995,
  "roe": 0.04378,
  "roa": 0.00232,
  "profit_margin": 0.03148,
  "operating_margin": 0.09287,
  "dividend_yield": 0.0252,
  "dividend_yield_trailing": 0.025233408,
  "payout_ratio": 0.4054,
  "revenue_growth": null,
  "earnings_growth": null,
  "debt_to_equity": null,
  "current_ratio": null,
  "free_cashflow": null,
  "beta": 0.029,
  "fifty_two_week_high": 2124.0,
  "fifty_two_week_low": 1191.0,
  "_market_data_updated": "2026-02-26T08:41:12.386859+00:00"
}