{
  "symbol": "6302.T",
  "name": "SUMITOMO HEAVY INDUSTRIES",
  "sector": "Industrials",
  "industry": "Specialty Industrial Machinery",
  "currency": "JPY",
  "price": 4962.0,
  "market_cap": 596340113408.0,
  "per": 19.265413,
  "forward_per": 14.847396,
  "pbr": 0.87482864,
  "psr": 0.55895656,
  "roe": 0.046729997,
  "roa": 0.024939999,
  "profit_margin": 0.029000001,
  "operating_margin": 0.05335,
  "dividend_yield": 0.029300000000000003,
  "dividend_yield_trailing": 0.024718212,
  "payout_ratio": 0.48560002,
  "revenue_growth": 0.049,
  "earnings_growth": null,
  "debt_to_equity": 36.825,
  "current_ratio": 1.921,
  "free_cashflow": 13478250496.0,
  "beta": 0.591,
  "fifty_two_week_high": 6362.0,
  "fifty_two_week_low": 2640.0,
  "_market_data_updated": "2026-04-07T08:57:38.191949+00:00"
}