{
  "symbol": "6525.T",
  "name": "KOKUSAI ELECTRIC CORPORATION",
  "sector": "Technology",
  "industry": "Semiconductor Equipment & Materials",
  "currency": "JPY",
  "price": 7054.0,
  "market_cap": 1646924398592.0,
  "per": 49.163647,
  "forward_per": 36.881733,
  "pbr": 7.7377033,
  "psr": 6.9395027,
  "roe": 0.16354,
  "roa": 0.07677,
  "profit_margin": 0.13808,
  "operating_margin": 0.17562,
  "dividend_yield": 0.49,
  "dividend_yield_trailing": 0.0050285403,
  "payout_ratio": 0.2582,
  "revenue_growth": -0.071,
  "earnings_growth": -0.094,
  "debt_to_equity": 26.236,
  "current_ratio": 2.204,
  "free_cashflow": 24064000000.0,
  "beta": 2.255,
  "fifty_two_week_high": 7651.0,
  "fifty_two_week_low": 2607.0,
  "_market_data_updated": "2026-05-11T10:57:50.131751+00:00"
}