{
  "symbol": "6645.T",
  "name": "OMRON CORP",
  "sector": "Technology",
  "industry": "Electronic Components",
  "currency": "JPY",
  "price": 5696.0,
  "market_cap": 1120001064960.0,
  "per": 32.777073,
  "forward_per": 21.013021,
  "pbr": 1.3398986,
  "psr": 1.4595681,
  "roe": 0.03822,
  "roa": 0.02611,
  "profit_margin": 0.03712,
  "operating_margin": 0.07836,
  "dividend_yield": 0.0179,
  "dividend_yield_trailing": 0.017894013,
  "payout_ratio": 0.5984,
  "revenue_growth": null,
  "earnings_growth": null,
  "debt_to_equity": 24.107,
  "current_ratio": 1.826,
  "free_cashflow": -65045626880.0,
  "beta": 1.133,
  "fifty_two_week_high": 6383.0,
  "fifty_two_week_low": 3503.0,
  "_market_data_updated": "2026-06-16T12:49:44.932989+00:00"
}