{
  "symbol": "6702.T",
  "name": "FUJITSU",
  "sector": "Technology",
  "industry": "Information Technology Services",
  "currency": "JPY",
  "price": 3313.0,
  "market_cap": 5788068216832.0,
  "per": 20.372648,
  "forward_per": 21.839157,
  "pbr": 2.9104266,
  "psr": 1.6107973,
  "roe": 0.16861,
  "roa": 0.06934,
  "profit_margin": 0.13232,
  "operating_margin": 0.11943,
  "dividend_yield": 0.0138,
  "dividend_yield_trailing": 0.007988981,
  "payout_ratio": 0.1783,
  "revenue_growth": -0.043,
  "earnings_growth": 0.602,
  "debt_to_equity": 6.68,
  "current_ratio": 1.912,
  "free_cashflow": 324066738176.0,
  "beta": 0.773,
  "fifty_two_week_high": 4668.0,
  "fifty_two_week_low": 2514.5,
  "_market_data_updated": "2026-02-24T08:41:27.077219+00:00"
}