{
  "symbol": "6758.T",
  "name": "SONY GROUP CORPORATION",
  "sector": "Technology",
  "industry": "Consumer Electronics",
  "currency": "JPY",
  "price": 3159.0,
  "market_cap": 18606089830400.0,
  "per": 18.413383,
  "forward_per": 17.24345,
  "pbr": 2.2985947,
  "psr": 1.490918,
  "roe": 0.12336001,
  "roa": 0.03944,
  "profit_margin": -0.02619,
  "operating_margin": 0.10738,
  "dividend_yield": 0.011000000000000001,
  "dividend_yield_trailing": 0.007854225,
  "payout_ratio": 0.1458,
  "revenue_growth": 0.083,
  "earnings_growth": -0.574,
  "debt_to_equity": 19.513,
  "current_ratio": 1.182,
  "free_cashflow": -1357953368064.0,
  "beta": 0.74,
  "fifty_two_week_high": 4776.0,
  "fifty_two_week_low": 3043.0,
  "_market_data_updated": "2026-06-23T10:59:00.687628+00:00"
}