{
  "symbol": "6841.T",
  "name": "YOKOGAWA ELECTRIC CORP",
  "sector": "Industrials",
  "industry": "Specialty Industrial Machinery",
  "currency": "JPY",
  "price": 5447.0,
  "market_cap": 1386964582400.0,
  "per": 24.695107,
  "forward_per": 25.208256,
  "pbr": 2.7448342,
  "psr": 2.3594575,
  "roe": 0.12224,
  "roa": 0.07281,
  "profit_margin": 0.09911,
  "operating_margin": 0.14072,
  "dividend_yield": 0.013999999999999999,
  "dividend_yield_trailing": 0.010924069,
  "payout_ratio": 0.2762,
  "revenue_growth": 0.07,
  "earnings_growth": 0.118,
  "debt_to_equity": 4.703,
  "current_ratio": 2.397,
  "free_cashflow": null,
  "beta": 0.689,
  "fifty_two_week_high": 6317.0,
  "fifty_two_week_low": 2944.0,
  "_market_data_updated": "2026-04-22T09:16:15.260765+00:00"
}