{
  "symbol": "6857.T",
  "name": "ADVANTEST CORP",
  "sector": "Technology",
  "industry": "Semiconductor Equipment & Materials",
  "currency": "JPY",
  "price": 31430.0,
  "market_cap": 22780894511104.0,
  "per": 61.06233,
  "forward_per": 132.20882,
  "pbr": 28.656797,
  "psr": 20.184914,
  "roe": 0.57646,
  "roa": 0.30794,
  "profit_margin": 0.33258,
  "operating_margin": 0.46671,
  "dividend_yield": 0.19,
  "dividend_yield_trailing": 0.0018340069,
  "payout_ratio": 0.1149,
  "revenue_growth": 0.412,
  "earnings_growth": 2.204,
  "debt_to_equity": 2.538,
  "current_ratio": 2.532,
  "free_cashflow": 240920756224.0,
  "beta": 1.199,
  "fifty_two_week_high": 33260.0,
  "fifty_two_week_low": 9661.0,
  "_market_data_updated": "2026-06-23T10:59:02.050716+00:00"
}