{
  "symbol": "6923.T",
  "name": "STANLEY ELECTRIC CO",
  "sector": "Consumer Cyclical",
  "industry": "Auto Parts",
  "currency": "JPY",
  "price": 3139.0,
  "market_cap": 385815445504.0,
  "per": 15.404622,
  "forward_per": 12.411039,
  "pbr": 0.8784184,
  "psr": 0.75067943,
  "roe": 0.07508,
  "roa": 0.03546,
  "profit_margin": 0.06704,
  "operating_margin": 0.07679,
  "dividend_yield": 0.032799999999999996,
  "dividend_yield_trailing": 0.028608164,
  "payout_ratio": 0.4365,
  "revenue_growth": -0.001,
  "earnings_growth": 0.768,
  "debt_to_equity": 19.165,
  "current_ratio": 2.452,
  "free_cashflow": null,
  "beta": null,
  "fifty_two_week_high": 3300.0,
  "fifty_two_week_low": 2615.5,
  "_market_data_updated": "2026-05-11T10:58:01.492193+00:00"
}