{
  "symbol": "6954.T",
  "name": "FANUC CORPORATION",
  "sector": "Industrials",
  "industry": "Specialty Industrial Machinery",
  "currency": "JPY",
  "price": 6256.0,
  "market_cap": 5837841498112.0,
  "per": 37.096775,
  "forward_per": 36.13887,
  "pbr": 3.2517858,
  "psr": 6.9878535,
  "roe": 0.093660004,
  "roa": 0.05585,
  "profit_margin": 0.19348,
  "operating_margin": 0.19347,
  "dividend_yield": 0.016200000000000003,
  "dividend_yield_trailing": 0.015963722,
  "payout_ratio": 0.6,
  "revenue_growth": 0.095,
  "earnings_growth": 0.127,
  "debt_to_equity": null,
  "current_ratio": 6.859,
  "free_cashflow": null,
  "beta": 0.778,
  "fifty_two_week_high": 7175.0,
  "fifty_two_week_low": 3581.0,
  "_market_data_updated": "2026-04-24T09:28:16.197879+00:00"
}