{
  "symbol": "6981.T",
  "name": "MURATA MANUFACTURING CO",
  "sector": "Technology",
  "industry": "Electronic Components",
  "currency": "JPY",
  "price": 7928.0,
  "market_cap": 14431269421056.0,
  "per": 62.117058,
  "forward_per": 33.41341,
  "pbr": 5.3080697,
  "psr": 7.882252,
  "roe": 0.08826,
  "roa": 0.06669,
  "profit_margin": 0.12777,
  "operating_margin": 0.28057,
  "dividend_yield": 0.98,
  "dividend_yield_trailing": 0.009116409,
  "payout_ratio": 0.5092,
  "revenue_growth": 0.118,
  "earnings_growth": 1.408,
  "debt_to_equity": 2.052,
  "current_ratio": 4.997,
  "free_cashflow": 115032498176.0,
  "beta": 1.099,
  "fifty_two_week_high": 8413.0,
  "fifty_two_week_low": 2018.5,
  "_market_data_updated": "2026-05-25T11:50:37.432842+00:00"
}