{
  "symbol": "7173.T",
  "name": "TOKYO KIRABOSHI FINANCIAL GP IN",
  "sector": "Financial Services",
  "industry": "Banks - Regional",
  "currency": "JPY",
  "price": 12210.0,
  "market_cap": 369854414848.0,
  "per": 13.557327,
  "forward_per": null,
  "pbr": 0.91126937,
  "psr": 2.4074361,
  "roe": 0.09907,
  "roa": 0.00546,
  "profit_margin": 0.24905,
  "operating_margin": 0.33841,
  "dividend_yield": 0.0139,
  "dividend_yield_trailing": 0.013854931,
  "payout_ratio": 0.18879999,
  "revenue_growth": -0.012,
  "earnings_growth": 0.451,
  "debt_to_equity": null,
  "current_ratio": null,
  "free_cashflow": null,
  "beta": 0.149,
  "fifty_two_week_high": 12540.0,
  "fifty_two_week_low": 4900.0,
  "_market_data_updated": "2026-04-15T09:14:35.838227+00:00"
}