{
  "symbol": "7180.T",
  "name": "KYUSHU FINANCIAL GROUP INC",
  "sector": "Financial Services",
  "industry": "Banks - Regional",
  "currency": "JPY",
  "price": 1301.0,
  "market_cap": 552926773248.0,
  "per": 15.385526,
  "forward_per": 17.323568,
  "pbr": 0.73332214,
  "psr": 2.415139,
  "roe": 0.05503,
  "roa": 0.0029499999,
  "profit_margin": 0.17648001,
  "operating_margin": 0.26785,
  "dividend_yield": 0.020099999999999996,
  "dividend_yield_trailing": 0.018532818,
  "payout_ratio": 0.284,
  "revenue_growth": 0.097,
  "earnings_growth": 0.616,
  "debt_to_equity": null,
  "current_ratio": null,
  "free_cashflow": null,
  "beta": 0.01,
  "fifty_two_week_high": 1436.5,
  "fifty_two_week_low": 606.0,
  "_market_data_updated": "2026-04-13T09:51:47.931341+00:00"
}