{
  "symbol": "7419.T",
  "name": "NOJIMA CORP",
  "sector": "Consumer Cyclical",
  "industry": "Specialty Retail",
  "currency": "JPY",
  "price": 1079.0,
  "market_cap": 311817273344.0,
  "per": 8.85297,
  "forward_per": 3.6440392,
  "pbr": 1.3234019,
  "psr": 0.32787082,
  "roe": 0.17813,
  "roa": 0.060289998,
  "profit_margin": 0.04039,
  "operating_margin": 0.05152,
  "dividend_yield": 0.014199999999999999,
  "dividend_yield_trailing": 0.013977211,
  "payout_ratio": 0.1258,
  "revenue_growth": 0.125,
  "earnings_growth": 0.075,
  "debt_to_equity": 36.41,
  "current_ratio": 1.516,
  "free_cashflow": null,
  "beta": null,
  "fifty_two_week_high": 1385.0,
  "fifty_two_week_low": 758.3333,
  "_market_data_updated": "2026-03-30T09:07:51.765429+00:00"
}