{
  "symbol": "7453.T",
  "name": "RYOHIN KEIKAKU CO",
  "sector": "Consumer Cyclical",
  "industry": "Department Stores",
  "currency": "JPY",
  "price": 3646.0,
  "market_cap": 1934752219136.0,
  "per": 38.058453,
  "forward_per": 23.150675,
  "pbr": 5.271102,
  "psr": 2.3734457,
  "roe": 0.16833,
  "roa": 0.08541001,
  "profit_margin": 0.07108,
  "operating_margin": 0.12437,
  "dividend_yield": 0.75,
  "dividend_yield_trailing": 0.0066542453,
  "payout_ratio": 0.2609,
  "revenue_growth": 0.154,
  "earnings_growth": 0.473,
  "debt_to_equity": 26.905,
  "current_ratio": 2.813,
  "free_cashflow": null,
  "beta": 0.576,
  "fifty_two_week_high": 3894.0,
  "fifty_two_week_low": 1915.0,
  "_market_data_updated": "2026-03-16T08:52:41.899194+00:00"
}