{
  "symbol": "7453.T",
  "name": "RYOHIN KEIKAKU CO",
  "sector": "Consumer Cyclical",
  "industry": "Department Stores",
  "currency": "JPY",
  "price": 3804.0,
  "market_cap": 2018594914304.0,
  "per": 33.924908,
  "forward_per": 24.153913,
  "pbr": 5.499526,
  "psr": 5.0257063,
  "roe": -0.04765,
  "roa": 0.03271,
  "profit_margin": -0.01726,
  "operating_margin": 0.03749,
  "dividend_yield": 0.85,
  "dividend_yield_trailing": 0.0048533333,
  "payout_ratio": 0.2672,
  "revenue_growth": -0.033,
  "earnings_growth": null,
  "debt_to_equity": 59.899,
  "current_ratio": 4.006,
  "free_cashflow": -7559249920.0,
  "beta": 1.006,
  "fifty_two_week_high": 3922.0,
  "fifty_two_week_low": 2035.0,
  "_market_data_updated": "2026-04-13T09:51:57.462768+00:00"
}