{
  "symbol": "7733.T",
  "name": "OLYMPUS CORPORATION",
  "sector": "Healthcare",
  "industry": "Medical Devices",
  "currency": "JPY",
  "price": 1785.5,
  "market_cap": 1966018396160.0,
  "per": 29.174837,
  "forward_per": 14.211239,
  "pbr": 2.4210858,
  "psr": 1.9452509,
  "roe": 0.08719,
  "roa": 0.05874,
  "profit_margin": 0.06745,
  "operating_margin": 0.16857,
  "dividend_yield": 0.0165,
  "dividend_yield_trailing": 0.016469942,
  "payout_ratio": 0.4902,
  "revenue_growth": 0.085,
  "earnings_growth": -0.387,
  "debt_to_equity": 29.503,
  "current_ratio": 1.617,
  "free_cashflow": 1487250048.0,
  "beta": 0.192,
  "fifty_two_week_high": 2168.0,
  "fifty_two_week_low": 1302.5,
  "_market_data_updated": "2026-05-29T11:24:49.119751+00:00"
}