{
  "symbol": "7733.T",
  "name": "OLYMPUS CORPORATION",
  "sector": "Healthcare",
  "industry": "Medical Devices",
  "currency": "JPY",
  "price": 1703.0,
  "market_cap": 1808855465984.0,
  "per": 27.795006,
  "forward_per": 13.554601,
  "pbr": 2.3092182,
  "psr": 1.7897481,
  "roe": 0.08719,
  "roa": 0.05874,
  "profit_margin": 0.06745,
  "operating_margin": 0.16857,
  "dividend_yield": 0.0172,
  "dividend_yield_trailing": 0.017236426,
  "payout_ratio": 0.4902,
  "revenue_growth": 0.085,
  "earnings_growth": -0.387,
  "debt_to_equity": 29.503,
  "current_ratio": 1.617,
  "free_cashflow": 1487250048.0,
  "beta": 0.209,
  "fifty_two_week_high": 2168.0,
  "fifty_two_week_low": 1302.5,
  "_market_data_updated": "2026-06-12T11:42:18.625224+00:00"
}