{
  "symbol": "7741.T",
  "name": "HOYA CORP",
  "sector": "Healthcare",
  "industry": "Medical Instruments & Supplies",
  "currency": "JPY",
  "price": 27470.0,
  "market_cap": 9215877840896.0,
  "per": 36.983185,
  "forward_per": 40.208435,
  "pbr": 9.031107,
  "psr": 9.723965,
  "roe": 0.25062,
  "roa": 0.15514,
  "profit_margin": 0.26704,
  "operating_margin": 0.46703,
  "dividend_yield": 0.010700000000000001,
  "dividend_yield_trailing": 0.0,
  "payout_ratio": 0.1681,
  "revenue_growth": 0.142,
  "earnings_growth": 0.075,
  "debt_to_equity": 4.081,
  "current_ratio": 4.812,
  "free_cashflow": 174866251776.0,
  "beta": 0.637,
  "fifty_two_week_high": 30400.0,
  "fifty_two_week_low": 16205.0,
  "_market_data_updated": "2026-05-08T09:13:25.772382+00:00"
}