{
  "symbol": "7751.T",
  "name": "CANON INC",
  "sector": "Technology",
  "industry": "Computer Hardware",
  "currency": "JPY",
  "price": 4370.0,
  "market_cap": 3773510189056.0,
  "per": 11.896011,
  "forward_per": 12.055506,
  "pbr": 1.1056296,
  "psr": 0.8097689,
  "roe": 0.09372,
  "roa": 0.045440003,
  "profit_margin": 0.06612,
  "operating_margin": 0.06526,
  "dividend_yield": 0.0369,
  "dividend_yield_trailing": 0.036934443,
  "payout_ratio": 0.4357,
  "revenue_growth": 0.033,
  "earnings_growth": -0.286,
  "debt_to_equity": 33.696,
  "current_ratio": 1.47,
  "free_cashflow": 68806877184.0,
  "beta": 0.251,
  "fifty_two_week_high": 5033.0,
  "fifty_two_week_low": 3956.0,
  "_market_data_updated": "2026-06-09T10:57:46.214972+00:00"
}