{
  "symbol": "7752.T",
  "name": "RICOH CO",
  "sector": "Industrials",
  "industry": "Business Equipment & Supplies",
  "currency": "JPY",
  "price": 1421.5,
  "market_cap": 809162375168.0,
  "per": 14.548153,
  "forward_per": 12.310556,
  "pbr": 0.7101155,
  "psr": 0.3102243,
  "roe": 0.05094,
  "roa": 0.024939999,
  "profit_margin": 0.021340001,
  "operating_margin": 0.03816,
  "dividend_yield": 0.0311,
  "dividend_yield_trailing": 0.0,
  "payout_ratio": 0.4096,
  "revenue_growth": 0.048,
  "earnings_growth": -0.506,
  "debt_to_equity": 43.818,
  "current_ratio": 1.494,
  "free_cashflow": 31070875648.0,
  "beta": 0.261,
  "fifty_two_week_high": 1585.5,
  "fifty_two_week_low": 1255.0,
  "_market_data_updated": "2026-05-15T10:18:45.481799+00:00"
}