{
  "symbol": "7956.T",
  "name": "PIGEON CORP",
  "sector": "Consumer Defensive",
  "industry": "Household & Personal Products",
  "currency": "JPY",
  "price": 1690.0,
  "market_cap": 202174758912.0,
  "per": 23.570433,
  "forward_per": 23.613245,
  "pbr": 2.43831,
  "psr": 1.851926,
  "roe": 0.103649996,
  "roa": 0.07532,
  "profit_margin": 0.0785,
  "operating_margin": 0.109239995,
  "dividend_yield": 0.0447,
  "dividend_yield_trailing": 0.044732194,
  "payout_ratio": 1.0606999,
  "revenue_growth": 0.018,
  "earnings_growth": -0.479,
  "debt_to_equity": 1.582,
  "current_ratio": 4.224,
  "free_cashflow": 7682625024.0,
  "beta": 0.214,
  "fifty_two_week_high": 1893.0,
  "fifty_two_week_low": 1567.0,
  "_market_data_updated": "2026-04-21T09:22:12.757193+00:00"
}