{
  "symbol": "7956.T",
  "name": "PIGEON CORP",
  "sector": "Consumer Defensive",
  "industry": "Household & Personal Products",
  "currency": "JPY",
  "price": 2036.0,
  "market_cap": 243596902400.0,
  "per": 28.435755,
  "forward_per": 28.447674,
  "pbr": 2.9851446,
  "psr": 2.1817906,
  "roe": 0.10804,
  "roa": 0.080469996,
  "profit_margin": 0.07656,
  "operating_margin": 0.13156,
  "dividend_yield": 0.0373,
  "dividend_yield_trailing": 0.037254903,
  "payout_ratio": 1.0606999,
  "revenue_growth": 0.098,
  "earnings_growth": -0.01,
  "debt_to_equity": null,
  "current_ratio": 3.907,
  "free_cashflow": null,
  "beta": 0.298,
  "fifty_two_week_high": 2130.5,
  "fifty_two_week_low": 1567.0,
  "_market_data_updated": "2026-07-14T09:53:35.305162+00:00"
}