{
  "symbol": "7956.T",
  "name": "PIGEON CORP",
  "sector": "Consumer Defensive",
  "industry": "Household & Personal Products",
  "currency": "JPY",
  "price": 1942.0,
  "market_cap": 232350285824.0,
  "per": 27.0813,
  "forward_per": 27.134274,
  "pbr": 2.8473237,
  "psr": 2.0810595,
  "roe": 0.10804,
  "roa": 0.080469996,
  "profit_margin": 0.07656,
  "operating_margin": 0.13156,
  "dividend_yield": 0.038900000000000004,
  "dividend_yield_trailing": 0.038894575,
  "payout_ratio": 1.0606999,
  "revenue_growth": 0.098,
  "earnings_growth": -0.01,
  "debt_to_equity": null,
  "current_ratio": 3.907,
  "free_cashflow": null,
  "beta": 0.301,
  "fifty_two_week_high": 2050.0,
  "fifty_two_week_low": 1567.0,
  "_market_data_updated": "2026-06-23T10:59:28.090815+00:00"
}