{
  "symbol": "8001.T",
  "name": "ITOCHU CORP",
  "sector": "Industrials",
  "industry": "Conglomerates",
  "currency": "JPY",
  "price": 1958.5,
  "market_cap": 13689620004864.0,
  "per": 14.727779,
  "forward_per": 3.0257852,
  "pbr": 2.1714184,
  "psr": 0.9331051,
  "roe": 0.14241,
  "roa": 0.02606,
  "profit_margin": 0.06196,
  "operating_margin": 0.0461,
  "dividend_yield": 0.0225,
  "dividend_yield_trailing": 0.020768432,
  "payout_ratio": 0.3008,
  "revenue_growth": -0.003,
  "earnings_growth": -0.124,
  "debt_to_equity": 70.966,
  "current_ratio": 1.3,
  "free_cashflow": 403272859648.0,
  "beta": 0.564,
  "fifty_two_week_high": 2286.5,
  "fifty_two_week_low": 1406.8,
  "_market_data_updated": "2026-04-29T10:02:50.606015+00:00"
}