{
  "symbol": "8031.T",
  "name": "MITSUI & CO",
  "sector": "Industrials",
  "industry": "Conglomerates",
  "currency": "JPY",
  "price": 4657.0,
  "market_cap": 13198815133696.0,
  "per": 16.008387,
  "forward_per": 15.848222,
  "pbr": 1.5053835,
  "psr": 0.9430944,
  "roe": 0.10301,
  "roa": 0.0159,
  "profit_margin": 0.05959,
  "operating_margin": 0.0379,
  "dividend_yield": 0.029900000000000003,
  "dividend_yield_trailing": 0.024588412,
  "payout_ratio": 0.39540002,
  "revenue_growth": -0.011,
  "earnings_growth": -0.093,
  "debt_to_equity": 63.294,
  "current_ratio": 1.408,
  "free_cashflow": -477800988672.0,
  "beta": 0.435,
  "fifty_two_week_high": 6675.0,
  "fifty_two_week_low": 2949.0,
  "_market_data_updated": "2026-07-08T10:12:50.952366+00:00"
}