{
  "symbol": "8035.T",
  "name": "TOKYO ELECTRON",
  "sector": "Technology",
  "industry": "Semiconductor Equipment & Materials",
  "currency": "JPY",
  "price": 47160.0,
  "market_cap": 21543499333632.0,
  "per": 37.69182,
  "forward_per": 36.837994,
  "pbr": 10.362692,
  "psr": 8.816537,
  "roe": 0.2927,
  "roa": 0.14237,
  "profit_margin": 0.23509,
  "operating_margin": 0.2889,
  "dividend_yield": 0.0147,
  "dividend_yield_trailing": 0.01274868,
  "payout_ratio": 0.50200003,
  "revenue_growth": 0.086,
  "earnings_growth": 0.505,
  "debt_to_equity": null,
  "current_ratio": 2.702,
  "free_cashflow": 229109252096.0,
  "beta": 1.366,
  "fifty_two_week_high": 53870.0,
  "fifty_two_week_low": 19870.0,
  "_market_data_updated": "2026-05-19T10:59:47.421715+00:00"
}