{
  "symbol": "8136.T",
  "name": "SANRIO CO LTD",
  "sector": "Consumer Cyclical",
  "industry": "Specialty Retail",
  "currency": "JPY",
  "price": 1161.0,
  "market_cap": 1407631491072.0,
  "per": 25.920963,
  "forward_per": 8.8511095,
  "pbr": 9.036004,
  "psr": 7.252543,
  "roe": 0.41667998,
  "roa": 0.22267,
  "profit_margin": 0.28136,
  "operating_margin": 0.30379,
  "dividend_yield": 0.013999999999999999,
  "dividend_yield_trailing": 0.012078775,
  "payout_ratio": 0.295,
  "revenue_growth": 0.269,
  "earnings_growth": 0.422,
  "debt_to_equity": 12.191,
  "current_ratio": 3.28,
  "free_cashflow": 40581873664.0,
  "beta": 0.221,
  "fifty_two_week_high": 1737.0,
  "fifty_two_week_low": 818.8,
  "_market_data_updated": "2026-07-13T10:56:11.763523+00:00"
}