{
  "symbol": "8331.T",
  "name": "CHIBA BANK",
  "sector": "Financial Services",
  "industry": "Banks - Regional",
  "currency": "JPY",
  "price": 2050.5,
  "market_cap": 1430935830528.0,
  "per": 16.359503,
  "forward_per": 18.58347,
  "pbr": 1.151516,
  "psr": 4.5265164,
  "roe": 0.07361,
  "roa": 0.00414,
  "profit_margin": 0.28004998,
  "operating_margin": 0.42058,
  "dividend_yield": 0.026699999999999998,
  "dividend_yield_trailing": 0.021909978,
  "payout_ratio": 0.3667,
  "revenue_growth": 0.312,
  "earnings_growth": 0.493,
  "debt_to_equity": null,
  "current_ratio": null,
  "free_cashflow": null,
  "beta": -0.087,
  "fifty_two_week_high": 2445.0,
  "fifty_two_week_low": 1000.5,
  "_market_data_updated": "2026-03-26T08:49:04.205178+00:00"
}