{
  "symbol": "8354.T",
  "name": "FUKUOKA FINANCIAL GROUP INC.",
  "sector": "Financial Services",
  "industry": "Banks - Regional",
  "currency": "JPY",
  "price": 6807.0,
  "market_cap": 1286285688832.0,
  "per": 16.806578,
  "forward_per": 16.735508,
  "pbr": 1.2232347,
  "psr": 3.6394665,
  "roe": null,
  "roa": null,
  "profit_margin": 0.2313,
  "operating_margin": 0.38415,
  "dividend_yield": 0.0279,
  "dividend_yield_trailing": 0.022680715,
  "payout_ratio": 0.3829,
  "revenue_growth": null,
  "earnings_growth": null,
  "debt_to_equity": null,
  "current_ratio": null,
  "free_cashflow": null,
  "beta": -0.126,
  "fifty_two_week_high": 7334.0,
  "fifty_two_week_low": 2917.0,
  "_market_data_updated": "2026-02-21T05:56:09.459794+00:00"
}