{
  "symbol": "8377.T",
  "name": "HOKUHOKU FINANCIAL GROUP INC",
  "sector": "Financial Services",
  "industry": "Banks - Regional",
  "currency": "JPY",
  "price": 6271.0,
  "market_cap": 756944601088.0,
  "per": 15.210906,
  "forward_per": 27.723253,
  "pbr": 1.0826955,
  "psr": 3.7138991,
  "roe": 0.077259995,
  "roa": 0.0031,
  "profit_margin": 0.25857002,
  "operating_margin": 0.375,
  "dividend_yield": 0.017,
  "dividend_yield_trailing": 0.011202102,
  "payout_ratio": 0.176,
  "revenue_growth": 0.122,
  "earnings_growth": 0.156,
  "debt_to_equity": null,
  "current_ratio": null,
  "free_cashflow": null,
  "beta": 0.157,
  "fifty_two_week_high": 6587.0,
  "fifty_two_week_low": 1911.0,
  "_market_data_updated": "2026-04-10T09:04:50.465575+00:00"
}