{
  "symbol": "8591.T",
  "name": "ORIX CORPORATION",
  "sector": "Financial Services",
  "industry": "Financial Conglomerates",
  "currency": "JPY",
  "price": 4704.0,
  "market_cap": 5166113226752.0,
  "per": 11.288156,
  "forward_per": 12.65741,
  "pbr": 1.1355579,
  "psr": 1.6509125,
  "roe": 0.106850006,
  "roa": 0.022939999,
  "profit_margin": 0.15005,
  "operating_margin": 0.19553,
  "dividend_yield": 0.0401,
  "dividend_yield_trailing": 0.03241394,
  "payout_ratio": 0.36400002,
  "revenue_growth": 0.125,
  "earnings_growth": 0.366,
  "debt_to_equity": 142.118,
  "current_ratio": 4.385,
  "free_cashflow": null,
  "beta": 0.527,
  "fifty_two_week_high": 5648.0,
  "fifty_two_week_low": 2559.0,
  "_market_data_updated": "2026-04-03T08:48:10.645380+00:00"
}