{
  "symbol": "8601.T",
  "name": "DAIWA SECURITIES GROUP",
  "sector": "Financial Services",
  "industry": "Capital Markets",
  "currency": "JPY",
  "price": 1879.0,
  "market_cap": 2605422215168.0,
  "per": 15.133698,
  "forward_per": 19.091648,
  "pbr": 1.4714854,
  "psr": 1.775049,
  "roe": 0.095860004,
  "roa": 0.00513,
  "profit_margin": 0.11942001,
  "operating_margin": 0.88216,
  "dividend_yield": 0.0388,
  "dividend_yield_trailing": 0.035516094,
  "payout_ratio": 0.5155,
  "revenue_growth": 0.047,
  "earnings_growth": 0.696,
  "debt_to_equity": 957.078,
  "current_ratio": 1.03,
  "free_cashflow": null,
  "beta": 0.5,
  "fifty_two_week_high": 1879.0,
  "fifty_two_week_low": 1007.0,
  "_market_data_updated": "2026-07-15T09:58:10.218438+00:00"
}