{
  "symbol": "8604.T",
  "name": "NOMURA HOLDINGS INC.",
  "sector": "Financial Services",
  "industry": "Capital Markets",
  "currency": "JPY",
  "price": 1204.0,
  "market_cap": 3522862514176.0,
  "per": 10.202525,
  "forward_per": 13.238044,
  "pbr": 0.967289,
  "psr": 1.7241323,
  "roe": 0.09928001,
  "roa": 0.00607,
  "profit_margin": 0.17627001,
  "operating_margin": 0.24507,
  "dividend_yield": 0.0449,
  "dividend_yield_trailing": 0.042394016,
  "payout_ratio": 0.4321,
  "revenue_growth": 0.099,
  "earnings_growth": -0.087,
  "debt_to_equity": 895.372,
  "current_ratio": 1.544,
  "free_cashflow": null,
  "beta": 0.478,
  "fifty_two_week_high": 1506.5,
  "fifty_two_week_low": 672.0,
  "_market_data_updated": "2026-03-31T08:54:29.921067+00:00"
}