{
  "symbol": "8729.T",
  "name": "SONY FINANCIAL GROUP INC",
  "sector": "Financial Services",
  "industry": "Insurance - Life",
  "currency": "JPY",
  "price": 137.5,
  "market_cap": 922411335680.0,
  "per": 17.741936,
  "forward_per": null,
  "pbr": 1.4658692,
  "psr": 0.3791606,
  "roe": 0.085439995,
  "roa": 0.0059100003,
  "profit_margin": 0.022809999,
  "operating_margin": 1.33435,
  "dividend_yield": 0.057699999999999994,
  "dividend_yield_trailing": 0.027417026,
  "payout_ratio": 0.4903,
  "revenue_growth": null,
  "earnings_growth": null,
  "debt_to_equity": 174.176,
  "current_ratio": 1.004,
  "free_cashflow": 38752624640.0,
  "beta": 0.012,
  "fifty_two_week_high": 210.0,
  "fifty_two_week_low": 129.3,
  "_market_data_updated": "2026-06-25T10:39:32.226495+00:00"
}