{
  "symbol": "8795.T",
  "name": "T&D HOLDINGS INC",
  "sector": "Financial Services",
  "industry": "Insurance - Life",
  "currency": "JPY",
  "price": 4954.0,
  "market_cap": 2377255223296.0,
  "per": 17.722607,
  "forward_per": 20.02749,
  "pbr": 1.4746106,
  "psr": 0.81405014,
  "roe": 0.09573,
  "roa": 0.01592,
  "profit_margin": 0.04759,
  "operating_margin": 0.63365,
  "dividend_yield": 0.0334,
  "dividend_yield_trailing": 0.026508972,
  "payout_ratio": 0.465,
  "revenue_growth": 0.102,
  "earnings_growth": 3.45,
  "debt_to_equity": 20.335,
  "current_ratio": 9.401,
  "free_cashflow": 46875500544.0,
  "beta": -0.002,
  "fifty_two_week_high": 5053.0,
  "fifty_two_week_low": 3124.0,
  "_market_data_updated": "2026-07-03T10:31:59.432461+00:00"
}