{
  "symbol": "8984.T",
  "name": "DAIWA HOUSE REIT INVESTMENT COR",
  "sector": "Real Estate",
  "industry": "REIT - Diversified",
  "currency": "JPY",
  "price": 129700.0,
  "market_cap": 595384991744.0,
  "per": 21.11776,
  "forward_per": 12.830913,
  "pbr": 0.58067375,
  "psr": 8.677058,
  "roe": 0.05924,
  "roa": 0.02219,
  "profit_margin": 0.43785998,
  "operating_margin": 0.4302,
  "dividend_yield": 0.045700000000000005,
  "dividend_yield_trailing": 0.05279969,
  "payout_ratio": 1.0,
  "revenue_growth": null,
  "earnings_growth": null,
  "debt_to_equity": 75.3,
  "current_ratio": 0.821,
  "free_cashflow": 23627999232.0,
  "beta": 0.206,
  "fifty_two_week_high": 144700.0,
  "fifty_two_week_low": 117700.0,
  "_market_data_updated": "2026-04-13T09:52:31.971900+00:00"
}