{
  "symbol": "9020.T",
  "name": "EAST JAPAN RAILWAY CO",
  "sector": "Industrials",
  "industry": "Railroads",
  "currency": "JPY",
  "price": 3313.0,
  "market_cap": 3739231715328.0,
  "per": 15.098209,
  "forward_per": 16.066925,
  "pbr": 1.2275918,
  "psr": 1.2121947,
  "roe": 0.08387,
  "roa": 0.02466,
  "profit_margin": 0.08035,
  "operating_margin": 0.07653,
  "dividend_yield": 0.025099999999999997,
  "dividend_yield_trailing": 0.022122571,
  "payout_ratio": 0.3373,
  "revenue_growth": 0.109,
  "earnings_growth": 2.718,
  "debt_to_equity": 158.822,
  "current_ratio": 0.776,
  "free_cashflow": -216981504000.0,
  "beta": 0.038,
  "fifty_two_week_high": 4211.0,
  "fifty_two_week_low": 2959.5,
  "_market_data_updated": "2026-06-03T12:40:01.001041+00:00"
}