{
  "symbol": "9023.T",
  "name": "TOKYO METRO CO LTD",
  "sector": "Industrials",
  "industry": "Railroads",
  "currency": "JPY",
  "price": 1514.0,
  "market_cap": 879025979392.0,
  "per": 14.898642,
  "forward_per": null,
  "pbr": 1.1963556,
  "psr": 2.0809584,
  "roe": 0.08133,
  "roa": 0.02747,
  "profit_margin": 0.13971,
  "operating_margin": 0.123500004,
  "dividend_yield": 0.028900000000000002,
  "dividend_yield_trailing": 0.0275681,
  "payout_ratio": 0.4133,
  "revenue_growth": 0.038,
  "earnings_growth": -0.351,
  "debt_to_equity": 145.832,
  "current_ratio": 1.658,
  "free_cashflow": 44652498944.0,
  "beta": null,
  "fifty_two_week_high": 1901.0,
  "fifty_two_week_low": 1492.0,
  "_market_data_updated": "2026-05-14T10:13:18.985061+00:00"
}