{
  "symbol": "9024.T",
  "name": "SEIBU HOLDINGS INC",
  "sector": "Industrials",
  "industry": "Conglomerates",
  "currency": "JPY",
  "price": 4592.0,
  "market_cap": 1166341439488.0,
  "per": 6.359054,
  "forward_per": 32.55814,
  "pbr": 2.1497905,
  "psr": 1.2841394,
  "roe": 0.42199,
  "roa": 0.10865,
  "profit_margin": 0.219,
  "operating_margin": 0.10564999,
  "dividend_yield": 0.86,
  "dividend_yield_trailing": 0.009721322,
  "payout_ratio": 0.0623,
  "revenue_growth": -0.001,
  "earnings_growth": -0.083,
  "debt_to_equity": 118.584,
  "current_ratio": 0.608,
  "free_cashflow": null,
  "beta": 0.413,
  "fifty_two_week_high": 5871.0,
  "fifty_two_week_low": 2961.5,
  "_market_data_updated": "2026-02-24T08:42:32.274837+00:00"
}