{
  "symbol": "9041.T",
  "name": "KINTETSU GROUP HOLDINGS CO LTD",
  "sector": "Industrials",
  "industry": "Conglomerates",
  "currency": "JPY",
  "price": 3302.0,
  "market_cap": 627894255616.0,
  "per": 12.915086,
  "forward_per": 12.296577,
  "pbr": 1.0736071,
  "psr": 0.35835153,
  "roe": 0.08518,
  "roa": 0.02187,
  "profit_margin": 0.02586,
  "operating_margin": 0.06593,
  "dividend_yield": 0.018600000000000002,
  "dividend_yield_trailing": 0.017080745,
  "payout_ratio": 0.2151,
  "revenue_growth": 0.017,
  "earnings_growth": -0.166,
  "debt_to_equity": 196.031,
  "current_ratio": 1.164,
  "free_cashflow": null,
  "beta": -0.167,
  "fifty_two_week_high": 3406.0,
  "fifty_two_week_low": 2630.0,
  "_market_data_updated": "2026-04-01T09:00:14.292854+00:00"
}