{
  "symbol": "9042.T",
  "name": "HANKYU HANSHIN HOLDINGS INC",
  "sector": "Industrials",
  "industry": "Conglomerates",
  "currency": "JPY",
  "price": 4548.0,
  "market_cap": 1078914908160.0,
  "per": 13.775557,
  "forward_per": 13.988251,
  "pbr": 0.9775201,
  "psr": 0.89647657,
  "roe": 0.07153,
  "roa": 0.02271,
  "profit_margin": 0.06526,
  "operating_margin": 0.03974,
  "dividend_yield": 0.021400000000000002,
  "dividend_yield_trailing": 0.021353833,
  "payout_ratio": 0.3028,
  "revenue_growth": 0.065,
  "earnings_growth": null,
  "debt_to_equity": 119.413,
  "current_ratio": 1.277,
  "free_cashflow": -78146502656.0,
  "beta": -0.082,
  "fifty_two_week_high": 5030.0,
  "fifty_two_week_low": 3728.0,
  "_market_data_updated": "2026-06-01T13:34:36.752087+00:00"
}