{
  "symbol": "9044.T",
  "name": "NANKAI CO LTD",
  "sector": "Real Estate",
  "industry": "Real Estate - Development",
  "currency": "JPY",
  "price": 2980.0,
  "market_cap": 322525134848.0,
  "per": 13.957846,
  "forward_per": 14.2966795,
  "pbr": 0.968899,
  "psr": 1.218391,
  "roe": 0.07723,
  "roa": 0.024449999,
  "profit_margin": 0.09495,
  "operating_margin": 0.08329,
  "dividend_yield": 0.018500000000000003,
  "dividend_yield_trailing": 0.0,
  "payout_ratio": 0.2226,
  "revenue_growth": -0.059,
  "earnings_growth": 0.314,
  "debt_to_equity": 129.192,
  "current_ratio": 0.68,
  "free_cashflow": null,
  "beta": null,
  "fifty_two_week_high": 3318.0,
  "fifty_two_week_low": 2120.0,
  "_market_data_updated": "2026-05-01T09:31:15.830403+00:00"
}