{
  "symbol": "9107.T",
  "name": "KAWASAKI KISEN KAISHA",
  "sector": "Industrials",
  "industry": "Marine Shipping",
  "currency": "JPY",
  "price": 2656.0,
  "market_cap": 1678842396672.0,
  "per": 8.851858,
  "forward_per": 7.6009502,
  "pbr": 0.96499705,
  "psr": 1.6610377,
  "roe": 0.07177,
  "roa": 0.02174,
  "profit_margin": 0.12197,
  "operating_margin": 0.09644,
  "dividend_yield": 0.0433,
  "dividend_yield_trailing": 0.040582918,
  "payout_ratio": 0.36650002,
  "revenue_growth": 0.001,
  "earnings_growth": -0.654,
  "debt_to_equity": 13.781,
  "current_ratio": 2.311,
  "free_cashflow": null,
  "beta": 1.065,
  "fifty_two_week_high": 2964.5,
  "fifty_two_week_low": 1571.5,
  "_market_data_updated": "2026-03-30T09:08:42.607657+00:00"
}