{
  "symbol": "9434.T",
  "name": "SOFTBANK CORP.",
  "sector": "Communication Services",
  "industry": "Telecom Services",
  "currency": "JPY",
  "price": 213.5,
  "market_cap": 10205570007040.0,
  "per": 18.9441,
  "forward_per": 18.421053,
  "pbr": 3.450338,
  "psr": 1.4499266,
  "roe": 0.16267,
  "roa": 0.0358,
  "profit_margin": 0.07825,
  "operating_margin": 0.08928,
  "dividend_yield": 0.0409,
  "dividend_yield_trailing": 0.040000003,
  "payout_ratio": 0.76309997,
  "revenue_growth": null,
  "earnings_growth": null,
  "debt_to_equity": 138.902,
  "current_ratio": 0.634,
  "free_cashflow": 1615376023552.0,
  "beta": 0.066,
  "fifty_two_week_high": 247.9,
  "fifty_two_week_low": 206.5,
  "_market_data_updated": "2026-06-12T11:43:15.226770+00:00"
}