{
  "symbol": "9504.T",
  "name": "CHUGOKU ELECTRIC POWER CO INC",
  "sector": "Utilities",
  "industry": "Utilities - Renewable",
  "currency": "JPY",
  "price": 1024.0,
  "market_cap": 368216997888.0,
  "per": 3.300245,
  "forward_per": 5.454061,
  "pbr": 0.4850499,
  "psr": 0.24732037,
  "roe": 0.12566,
  "roa": 0.01959,
  "profit_margin": 0.06041,
  "operating_margin": 0.02552,
  "dividend_yield": 0.0265,
  "dividend_yield_trailing": 0.03137255,
  "payout_ratio": 0.1031,
  "revenue_growth": -0.07,
  "earnings_growth": -0.799,
  "debt_to_equity": 435.779,
  "current_ratio": 1.324,
  "free_cashflow": null,
  "beta": 0.173,
  "fifty_two_week_high": 1145.0,
  "fifty_two_week_low": 677.2,
  "_market_data_updated": "2026-04-03T08:48:36.832112+00:00"
}