{
  "symbol": "9533.T",
  "name": "TOHO GAS CO",
  "sector": "Utilities",
  "industry": "Utilities - Regulated Gas",
  "currency": "JPY",
  "price": 1211.5,
  "market_cap": 438332850176.0,
  "per": 14.463944,
  "forward_per": 5.4510684,
  "pbr": 0.9234184,
  "psr": 0.6732344,
  "roe": 0.067930005,
  "roa": 0.02533,
  "profit_margin": 0.048299998,
  "operating_margin": 0.03212,
  "dividend_yield": 0.0189,
  "dividend_yield_trailing": 0.01888376,
  "payout_ratio": 0.26860002,
  "revenue_growth": -0.05,
  "earnings_growth": null,
  "debt_to_equity": 32.133,
  "current_ratio": 1.643,
  "free_cashflow": 9720000512.0,
  "beta": -0.01,
  "fifty_two_week_high": 1425.75,
  "fifty_two_week_low": 987.25,
  "_market_data_updated": "2026-06-05T11:25:00.177066+00:00"
}