{
  "symbol": "9984.T",
  "name": "SOFTBANK GROUP CORP",
  "sector": "Communication Services",
  "industry": "Telecom Services",
  "currency": "JPY",
  "price": 3544.0,
  "market_cap": 20196418912256.0,
  "per": 6.6261573,
  "forward_per": 12.0017605,
  "pbr": 1.3075976,
  "psr": 2.6364627,
  "roe": 0.26023,
  "roa": 0.00695,
  "profit_margin": 0.48167,
  "operating_margin": 0.03838,
  "dividend_yield": 0.3,
  "dividend_yield_trailing": 0.0030479357,
  "payout_ratio": 0.020599999,
  "revenue_growth": 0.082,
  "earnings_growth": null,
  "debt_to_equity": 132.434,
  "current_ratio": 0.832,
  "free_cashflow": -53278248960.0,
  "beta": 0.611,
  "fifty_two_week_high": 6923.75,
  "fifty_two_week_low": 1432.5,
  "_market_data_updated": "2026-03-17T08:48:18.846893+00:00"
}